Workbook

Sheet Cleaned Data
A1: Order ID | B1: Order Date | C1: Customer Name | D1: Region | E1: Category | F1: Product Name | G1: Sales | H1: Quantity | I1: Profit | J1: Discount
A2: ORD-1243 | B2: 44928 | C2: Sneha Mehta | D2: South | E2: Office Supplies | F2: Sticky Notes | G2: 468.3 | H2: 12 | I2: 100.7 | J2: 0.15
A3: ORD-1077 | B3: 44928 | C3: Gaurav Nair | D3: North | E3: Office Supplies | F3: Sticky Notes | G3: 171.56 | H3: 5 | I3: 22.23 | J3: 0.3
A4: ORD-1077 | B4: 44928 | C4: Gaurav Nair | D4: North | E4: Office Supplies | F4: Sticky Notes | G4: 171.56 | H4: 5 | I4: 22.23 | J4: 0.3
A5: ORD-1135 | B5: 44929 | C5: Vikram Mehta | D5: South | E5: Office Supplies | F5: Notebook Pack | G5: 25.1 | H5: 2 | I5: -0.92 | J5: 0.2
A6: ORD-1205 | B6: 44930 | C6: Swati Sharma | D6: South | E6: Technology | F6: Webcam HD | G6: 673.99 | H6: 9 | I6: 189.11 | J6: 0.1
A7: ORD-1026 | B7: 44931 | C7: Preeti Rao | D7: North | E7: Furniture | F7: Sofa Set | G7: 3756.21 | H7: 11 | I7: 485.83 | J7: 0
A8: ORD-1061 | B8: 44934 | C8: Neha Nair | D8: North | E8: Office Supplies | F8: Notebook Pack | G8: 175.21 | H8: 12 | I8: 34.91 | J8: 0.1
A9: ORD-1166 | B9: 44935 | C9: Deepak Nair | D9: South | E9: Technology | F9: Webcam HD | G9: 245.28 | H9: 1 | I9: 56.18 | J9: 0.1
A10: ORD-1308 | B10: 44937 | C10: Suresh Rao | D10: North | E10: Technology | F10: Laptop Stand | G10: 1838.46 | H10: 11 | I10: 215.34 | J10: 0
A11: ORD-1190 | B11: 44938 | C11: Meera Sharma | D11: West | E11: Technology | F11: Bluetooth Speaker | G11: 573.35 | H11: 5 | I11: 101.49 | J11: 0.2
A12: ORD-1016 | B12: 44943 | C12: Meera Verma | D12: East | E12: Furniture | F12: Office Chair | G12: 616.05 | H12: 6 | I12: 111.98 | J12: 0.05
A13: ORD-1296 | B13: 44944 | C13: Ananya Gupta | D13: North | E13: Furniture | F13: Furniture - Unspecified | G13: 2365.11 | H13: 9 | I13: 203.6 | J13: 0
... A320: ORD-1132 | B320: 45291 | C320: Nisha Verma | D320: North | E320: Furniture | F320: Sofa Set | G320: 3171.36 | H320: 9 | I320: 395.77 | J320: 0.1

Sheet Summary Metrics
A1: Business Summary Metrics
A3: Metric | B3: Value
A4: Total Sales | B4: =SUM('Cleaned Data'!G2:G320) -> 263274.38
A5: Total Profit | B5: =SUM('Cleaned Data'!I2:I320) -> 36093.52
A6: Total Orders | B6: =COUNTA('Cleaned Data'!A2:A320) -> 319
A7: Average Order Value | B7: =AVERAGE('Cleaned Data'!G2:G320) -> 825.31154
A8: Total Quantity Sold | B8: =SUM('Cleaned Data'!H2:H320) -> 2060

Sheet Sales by Region
A1: Sales & Profit by Region
A3: Region | B3: Total Sales | C3: Total Profit | D3: Total Orders
A4: East | B4: =SUMIF('Cleaned Data'!$D$2:$D$320,A4,'Cleaned Data'!$G$2:$G$320) -> 69243.21 | C4: =SUMIF('Cleaned Data'!$D$2:$D$320,A4,'Cleaned Data'!$I$2:$I$320) -> 9716.39 | D4: =COUNTIF('Cleaned Data'!$D$2:$D$320,A4) -> 89
A5: West | B5: =SUMIF('Cleaned Data'!$D$2:$D$320,A5,'Cleaned Data'!$G$2:$G$320) -> 68967.2 | C5: =SUMIF('Cleaned Data'!$D$2:$D$320,A5,'Cleaned Data'!$I$2:$I$320) -> 9450 | D5: =COUNTIF('Cleaned Data'!$D$2:$D$320,A5) -> 75
A6: North | B6: =SUMIF('Cleaned Data'!$D$2:$D$320,A6,'Cleaned Data'!$G$2:$G$320) -> 69914.24 | C6: =SUMIF('Cleaned Data'!$D$2:$D$320,A6,'Cleaned Data'!$I$2:$I$320) -> 8560.92 | D6: =COUNTIF('Cleaned Data'!$D$2:$D$320,A6) -> 77
A7: South | B7: =SUMIF('Cleaned Data'!$D$2:$D$320,A7,'Cleaned Data'!$G$2:$G$320) -> 55149.73 | C7: =SUMIF('Cleaned Data'!$D$2:$D$320,A7,'Cleaned Data'!$I$2:$I$320) -> 8366.21 | D7: =COUNTIF('Cleaned Data'!$D$2:$D$320,A7) -> 78

Sheet Profit by Category
A1: Profit & Sales by Category
A3: Category | B3: Total Profit | C3: Total Sales | D3: Profit Margin %
A4: Furniture | B4: =SUMIF('Cleaned Data'!$E$2:$E$320,A4,'Cleaned Data'!$I$2:$I$320) -> 21877.13 | C4: =SUMIF('Cleaned Data'!$E$2:$E$320,A4,'Cleaned Data'!$G$2:$G$320) -> 160269.79 | D4: =B4/C4 -> 0.13650189
A5: Office Supplies | B5: =SUMIF('Cleaned Data'!$E$2:$E$320,A5,'Cleaned Data'!$I$2:$I$320) -> 2073.24 | C5: =SUMIF('Cleaned Data'!$E$2:$E$320,A5,'Cleaned Data'!$G$2:$G$320) -> 16433.5 | D5: =B5/C5 -> 0.12615937
A6: Technology | B6: =SUMIF('Cleaned Data'!$E$2:$E$320,A6,'Cleaned Data'!$I$2:$I$320) -> 12143.15 | C6: =SUMIF('Cleaned Data'!$E$2:$E$320,A6,'Cleaned Data'!$G$2:$G$320) -> 86571.09 | D6: =B6/C6 -> 0.14026796

Sheet Sales by Month
A1: Monthly Sales Trend
A3: Month | B3: Total Sales | C3: Total Profit | D3: Total Orders
A4: Jan | B4: =SUMPRODUCT((MONTH('Cleaned Data'!$B$2:$B$320)=1)*'Cleaned Data'!$G$2:$G$320) -> 14544.19 | C4: =SUMPRODUCT((MONTH('Cleaned Data'!$B$2:$B$320)=1)*'Cleaned Data'!$I$2:$I$320) -> 1792.68 | D4: =SUMPRODUCT((MONTH('Cleaned Data'!$B$2:$B$320)=1)*1) -> 25
A5: Feb | B5: =SUMPRODUCT((MONTH('Cleaned Data'!$B$2:$B$320)=2)*'Cleaned Data'!$G$2:$G$320) -> 22738.8 | C5: =SUMPRODUCT((MONTH('Cleaned Data'!$B$2:$B$320)=2)*'Cleaned Data'!$I$2:$I$320) -> 3592.85 | D5: =SUMPRODUCT((MONTH('Cleaned Data'!$B$2:$B$320)=2)*1) -> 22
A6: Mar | B6: =SUMPRODUCT((MONTH('Cleaned Data'!$B$2:$B$320)=3)*'Cleaned Data'!$G$2:$G$320) -> 25020.49 | C6: =SUMPRODUCT((MONTH('Cleaned Data'!$B$2:$B$320)=3)*'Cleaned Data'!$I$2:$I$320) -> 3201.84 | D6: =SUMPRODUCT((MONTH('Cleaned Data'!$B$2:$B$320)=3)*1) -> 28
A7: Apr | B7: =SUMPRODUCT((MONTH('Cleaned Data'!$B$2:$B$320)=4)*'Cleaned Data'!$G$2:$G$320) -> 32012.1 | C7: =SUMPRODUCT((MONTH('Cleaned Data'!$B$2:$B$320)=4)*'Cleaned Data'!$I$2:$I$320) -> 4182.01 | D7: =SUMPRODUCT((MONTH('Cleaned Data'!$B$2:$B$320)=4)*1) -> 35
A8: May | B8: =SUMPRODUCT((MONTH('Cleaned Data'!$B$2:$B$320)=5)*'Cleaned Data'!$G$2:$G$320) -> 21080.57 | C8: =SUMPRODUCT((MONTH('Cleaned Data'!$B$2:$B$320)=5)*'Cleaned Data'!$I$2:$I$320) -> 3864.11 | D8: =SUMPRODUCT((MONTH('Cleaned Data'!$B$2:$B$320)=5)*1) -> 34
A9: Jun | B9: =SUMPRODUCT((MONTH('Cleaned Data'!$B$2:$B$320)=6)*'Cleaned Data'!$G$2:$G$320) -> 15999.27 | C9: =SUMPRODUCT((MONTH('Cleaned Data'!$B$2:$B$320)=6)*'Cleaned Data'!$I$2:$I$320) -> 2128.92 | D9: =SUMPRODUCT((MONTH('Cleaned Data'!$B$2:$B$320)=6)*1) -> 24
A10: Jul | B10: =SUMPRODUCT((MONTH('Cleaned Data'!$B$2:$B$320)=7)*'Cleaned Data'!$G$2:$G$320) -> 22253.83 | C10: =SUMPRODUCT((MONTH('Cleaned Data'!$B$2:$B$320)=7)*'Cleaned Data'!$I$2:$I$320) -> 4746.46 | D10: =SUMPRODUCT((MONTH('Cleaned Data'!$B$2:$B$320)=7)*1) -> 21
A11: Aug | B11: =SUMPRODUCT((MONTH('Cleaned Data'!$B$2:$B$320)=8)*'Cleaned Data'!$G$2:$G$320) -> 23114.09 | C11: =SUMPRODUCT((MONTH('Cleaned Data'!$B$2:$B$320)=8)*'Cleaned Data'!$I$2:$I$320) -> 2513.65 | D11: =SUMPRODUCT((MONTH('Cleaned Data'!$B$2:$B$320)=8)*1) -> 29
A12: Sep | B12: =SUMPRODUCT((MONTH('Cleaned Data'!$B$2:$B$320)=9)*'Cleaned Data'!$G$2:$G$320) -> 20246.47 | C12: =SUMPRODUCT((MONTH('Cleaned Data'!$B$2:$B$320)=9)*'Cleaned Data'!$I$2:$I$320) -> 3024.76 | D12: =SUMPRODUCT((MONTH('Cleaned Data'!$B$2:$B$320)=9)*1) -> 22
A13: Oct | B13: =SUMPRODUCT((MONTH('Cleaned Data'!$B$2:$B$320)=10)*'Cleaned Data'!$G$2:$G$320) -> 18979.4 | C13: =SUMPRODUCT((MONTH('Cleaned Data'!$B$2:$B$320)=10)*'Cleaned Data'!$I$2:$I$320) -> 1502.85 | D13: =SUMPRODUCT((MONTH('Cleaned Data'!$B$2:$B$320)=10)*1) -> 24
A14: Nov | B14: =SUMPRODUCT((MONTH('Cleaned Data'!$B$2:$B$320)=11)*'Cleaned Data'!$G$2:$G$320) -> 24123.72 | C14: =SUMPRODUCT((MONTH('Cleaned Data'!$B$2:$B$320)=11)*'Cleaned Data'!$I$2:$I$320) -> 3397.08 | D14: =SUMPRODUCT((MONTH('Cleaned Data'!$B$2:$B$320)=11)*1) -> 26
A15: Dec | B15: =SUMPRODUCT((MONTH('Cleaned Data'!$B$2:$B$320)=12)*'Cleaned Data'!$G$2:$G$320) -> 23161.45 | C15: =SUMPRODUCT((MONTH('Cleaned Data'!$B$2:$B$320)=12)*'Cleaned Data'!$I$2:$I$320) -> 2146.31 | D15: =SUMPRODUCT((MONTH('Cleaned Data'!$B$2:$B$320)=12)*1) -> 29

Sheet Top 10 Customers
A1: Top 10 Customers by Sales
A3: Customer Name | B3: Total Sales | C3: Rank Key | E3: TOP 10 CUSTOMERS
A4: Aarav Mehta | B4: =SUMIF('Cleaned Data'!$C$2:$C$320,A4,'Cleaned Data'!$G$2:$G$320) -> 1865.51 | C4: =B4+ROW()/10000000 -> 1865.51 | E4: Rank | F4: Customer Name | G4: Total Sales
A5: Aarav Patel | B5: =SUMIF('Cleaned Data'!$C$2:$C$320,A5,'Cleaned Data'!$G$2:$G$320) -> 456.45 | C5: =B5+ROW()/10000000 -> 456.45 | E5: 1 | F5: =INDEX($A$4:$A$227,MATCH(LARGE($C$4:$C$227,1),$C$4:$C$227,0)) -> Neha Singh | G5: =INDEX($B$4:$B$227,MATCH(LARGE($C$4:$C$227,1),$C$4:$C$227,0)) -> 7080.04
A6: Aarav Singh | B6: =SUMIF('Cleaned Data'!$C$2:$C$320,A6,'Cleaned Data'!$G$2:$G$320) -> 83.44 | C6: =B6+ROW()/10000000 -> 83.440001 | E6: 2 | F6: =INDEX($A$4:$A$227,MATCH(LARGE($C$4:$C$227,2),$C$4:$C$227,0)) -> Gaurav Rao | G6: =INDEX($B$4:$B$227,MATCH(LARGE($C$4:$C$227,2),$C$4:$C$227,0)) -> 6388.51
A7: Aditya Gupta | B7: =SUMIF('Cleaned Data'!$C$2:$C$320,A7,'Cleaned Data'!$G$2:$G$320) -> 1512.35 | C7: =B7+ROW()/10000000 -> 1512.35 | E7: 3 | F7: =INDEX($A$4:$A$227,MATCH(LARGE($C$4:$C$227,3),$C$4:$C$227,0)) -> Vikram Mehta | G7: =INDEX($B$4:$B$227,MATCH(LARGE($C$4:$C$227,3),$C$4:$C$227,0)) -> 6367.53
A8: Aditya Nair | B8: =SUMIF('Cleaned Data'!$C$2:$C$320,A8,'Cleaned Data'!$G$2:$G$320) -> 222.2 | C8: =B8+ROW()/10000000 -> 222.2 | E8: 4 | F8: =INDEX($A$4:$A$227,MATCH(LARGE($C$4:$C$227,4),$C$4:$C$227,0)) -> Preeti Rao | G8: =INDEX($B$4:$B$227,MATCH(LARGE($C$4:$C$227,4),$C$4:$C$227,0)) -> 5264.59
A9: Aditya Patel | B9: =SUMIF('Cleaned Data'!$C$2:$C$320,A9,'Cleaned Data'!$G$2:$G$320) -> 186.74 | C9: =B9+ROW()/10000000 -> 186.74 | E9: 5 | F9: =INDEX($A$4:$A$227,MATCH(LARGE($C$4:$C$227,5),$C$4:$C$227,0)) -> Rohan Nair | G9: =INDEX($B$4:$B$227,MATCH(LARGE($C$4:$C$227,5),$C$4:$C$227,0)) -> 4271.68
A10: Aditya Reddy | B10: =SUMIF('Cleaned Data'!$C$2:$C$320,A10,'Cleaned Data'!$G$2:$G$320) -> 2120.27 | C10: =B10+ROW()/10000000 -> 2120.27 | E10: 6 | F10: =INDEX($A$4:$A$227,MATCH(LARGE($C$4:$C$227,6),$C$4:$C$227,0)) -> Nisha Iyer | G10: =INDEX($B$4:$B$227,MATCH(LARGE($C$4:$C$227,6),$C$4:$C$227,0)) -> 4171.31
A11: Aditya Sharma | B11: =SUMIF('Cleaned Data'!$C$2:$C$320,A11,'Cleaned Data'!$G$2:$G$320) -> 176.24 | C11: =B11+ROW()/10000000 -> 176.24 | E11: 7 | F11: =INDEX($A$4:$A$227,MATCH(LARGE($C$4:$C$227,7),$C$4:$C$227,0)) -> Ananya Patel | G11: =INDEX($B$4:$B$227,MATCH(LARGE($C$4:$C$227,7),$C$4:$C$227,0)) -> 3773.33
A12: Aditya Singh | B12: =SUMIF('Cleaned Data'!$C$2:$C$320,A12,'Cleaned Data'!$G$2:$G$320) -> 3299.09 | C12: =B12+ROW()/10000000 -> 3299.09 | E12: 8 | F12: =INDEX($A$4:$A$227,MATCH(LARGE($C$4:$C$227,8),$C$4:$C$227,0)) -> Vihaan Reddy | G12: =INDEX($B$4:$B$227,MATCH(LARGE($C$4:$C$227,8),$C$4:$C$227,0)) -> 3714.22
A13: Aditya Verma | B13: =SUMIF('Cleaned Data'!$C$2:$C$320,A13,'Cleaned Data'!$G$2:$G$320) -> 300.24 | C13: =B13+ROW()/10000000 -> 300.24 | E13: 9 | F13: =INDEX($A$4:$A$227,MATCH(LARGE($C$4:$C$227,9),$C$4:$C$227,0)) -> Ritu Mehta | G13: =INDEX($B$4:$B$227,MATCH(LARGE($C$4:$C$227,9),$C$4:$C$227,0)) -> 3676.52
A14: Akash Gupta | B14: =SUMIF('Cleaned Data'!$C$2:$C$320,A14,'Cleaned Data'!$G$2:$G$320) -> 273.63 | C14: =B14+ROW()/10000000 -> 273.63 | E14: 10 | F14: =INDEX($A$4:$A$227,MATCH(LARGE($C$4:$C$227,10),$C$4:$C$227,0)) -> Tanvi Gupta | G14: =INDEX($B$4:$B$227,MATCH(LARGE($C$4:$C$227,10),$C$4:$C$227,0)) -> 3563.51
A15: Akash Nair | B15: =SUMIF('Cleaned Data'!$C$2:$C$320,A15,'Cleaned Data'!$G$2:$G$320) -> 105.46 | C15: =B15+ROW()/10000000 -> 105.46
A16: Akash Patel | B16: =SUMIF('Cleaned Data'!$C$2:$C$320,A16,'Cleaned Data'!$G$2:$G$320) -> 720.07 | C16: =B16+ROW()/10000000 -> 720.07
A17: Akash Rao | B17: =SUMIF('Cleaned Data'!$C$2:$C$320,A17,'Cleaned Data'!$G$2:$G$320) -> 1154.68 | C17: =B17+ROW()/10000000 -> 1154.68
A18: Akash Sharma | B18: =SUMIF('Cleaned Data'!$C$2:$C$320,A18,'Cleaned Data'!$G$2:$G$320) -> 1268.86 | C18: =B18+ROW()/10000000 -> 1268.86
A19: Amit Gupta | B19: =SUMIF('Cleaned Data'!$C$2:$C$320,A19,'Cleaned Data'!$G$2:$G$320) -> 107.84 | C19: =B19+ROW()/10000000 -> 107.84
A20: Amit Reddy | B20: =SUMIF('Cleaned Data'!$C$2:$C$320,A20,'Cleaned Data'!$G$2:$G$320) -> 1188.06 | C20: =B20+ROW()/10000000 -> 1188.06
A21: Amit Sharma | B21: =SUMIF('Cleaned Data'!$C$2:$C$320,A21,'Cleaned Data'!$G$2:$G$320) -> 2135.97 | C21: =B21+ROW()/10000000 -> 2135.97
A22: Amit Verma | B22: =SUMIF('Cleaned Data'!$C$2:$C$320,A22,'Cleaned Data'!$G$2:$G$320) -> 171.19 | C22: =B22+ROW()/10000000 -> 171.19
A23: Ananya Gupta | B23: =SUMIF('Cleaned Data'!$C$2:$C$320,A23,'Cleaned Data'!$G$2:$G$320) -> 2609.98 | C23: =B23+ROW()/10000000 -> 2609.98
A24: Ananya Mehta | B24: =SUMIF('Cleaned Data'!$C$2:$C$320,A24,'Cleaned Data'!$G$2:$G$320) -> 2986.03 | C24: =B24+ROW()/10000000 -> 2986.03
A25: Ananya Nair | B25: =SUMIF('Cleaned Data'!$C$2:$C$320,A25,'Cleaned Data'!$G$2:$G$320) -> 190.31 | C25: =B25+ROW()/10000000 -> 190.31
A26: Ananya Patel | B26: =SUMIF('Cleaned Data'!$C$2:$C$320,A26,'Cleaned Data'!$G$2:$G$320) -> 3773.33 | C26: =B26+ROW()/10000000 -> 3773.33
... A227: Vikram Verma | B227: =SUMIF('Cleaned Data'!$C$2:$C$320,A227,'Cleaned Data'!$G$2:$G$320) -> 1460.92 | C227: =B227+ROW()/10000000 -> 1460.92

Sheet Top 5 Products
A1: Top 5 Products by Sales
A3: Product Name | B3: Total Sales | C3: Rank Key
A4: Bluetooth Speaker | B4: =SUMIF('Cleaned Data'!$F$2:$F$320,A4,'Cleaned Data'!$G$2:$G$320) -> 12889.89 | C4: =B4+ROW()/10000000 -> 12889.89
A5: Bookcase | B5: =SUMIF('Cleaned Data'!$F$2:$F$320,A5,'Cleaned Data'!$G$2:$G$320) -> 28429.83 | C5: =B5+ROW()/10000000 -> 28429.83
A6: Desk Organizer | B6: =SUMIF('Cleaned Data'!$F$2:$F$320,A6,'Cleaned Data'!$G$2:$G$320) -> 3349.24 | C6: =B6+ROW()/10000000 -> 3349.24
A7: Filing Cabinet | B7: =SUMIF('Cleaned Data'!$F$2:$F$320,A7,'Cleaned Data'!$G$2:$G$320) -> 24391.89 | C7: =B7+ROW()/10000000 -> 24391.89
A8: Furniture - Unspecified | B8: =SUMIF('Cleaned Data'!$F$2:$F$320,A8,'Cleaned Data'!$G$2:$G$320) -> 7174.2 | C8: =B8+ROW()/10000000 -> 7174.2
A9: Laptop Stand | B9: =SUMIF('Cleaned Data'!$F$2:$F$320,A9,'Cleaned Data'!$G$2:$G$320) -> 18627.8 | C9: =B9+ROW()/10000000 -> 18627.8
A10: Notebook Pack | B10: =SUMIF('Cleaned Data'!$F$2:$F$320,A10,'Cleaned Data'!$G$2:$G$320) -> 2566.21 | C10: =B10+ROW()/10000000 -> 2566.21
A11: Office Chair | B11: =SUMIF('Cleaned Data'!$F$2:$F$320,A11,'Cleaned Data'!$G$2:$G$320) -> 36010.99 | C11: =B11+ROW()/10000000 -> 36010.99
A12: Office Supplies - Unspecified | B12: =SUMIF('Cleaned Data'!$F$2:$F$320,A12,'Cleaned Data'!$G$2:$G$320) -> 311.9 | C12: =B12+ROW()/10000000 -> 311.9
A13: Printer Paper | B13: =SUMIF('Cleaned Data'!$F$2:$F$320,A13,'Cleaned Data'!$G$2:$G$320) -> 3195.2 | C13: =B13+ROW()/10000000 -> 3195.2
A14: Sofa Set | B14: =SUMIF('Cleaned Data'!$F$2:$F$320,A14,'Cleaned Data'!$G$2:$G$320) -> 31308.8 | C14: =B14+ROW()/10000000 -> 31308.8
A15: Stapler | B15: =SUMIF('Cleaned Data'!$F$2:$F$320,A15,'Cleaned Data'!$G$2:$G$320) -> 3891.89 | C15: =B15+ROW()/10000000 -> 3891.89
... A21: Wireless Mouse | B21: =SUMIF('Cleaned Data'!$F$2:$F$320,A21,'Cleaned Data'!$G$2:$G$320) -> 16693.65 | C21: =B21+ROW()/10000000 -> 16693.65
A23: TOP 5 PRODUCTS
A24: Rank | B24: Product Name | C24: Total Sales
A25: 1 | B25: =INDEX($A$4:$A$21,MATCH(LARGE($C$4:$C$21,1),$C$4:$C$21,0)) -> Office Chair | C25: =INDEX($B$4:$B$21,MATCH(LARGE($C$4:$C$21,1),$C$4:$C$21,0)) -> 36010.99
A26: 2 | B26: =INDEX($A$4:$A$21,MATCH(LARGE($C$4:$C$21,2),$C$4:$C$21,0)) -> Study Table | C26: =INDEX($B$4:$B$21,MATCH(LARGE($C$4:$C$21,2),$C$4:$C$21,0)) -> 32954.08
A27: 3 | B27: =INDEX($A$4:$A$21,MATCH(LARGE($C$4:$C$21,3),$C$4:$C$21,0)) -> Sofa Set | C27: =INDEX($B$4:$B$21,MATCH(LARGE($C$4:$C$21,3),$C$4:$C$21,0)) -> 31308.8
A28: 4 | B28: =INDEX($A$4:$A$21,MATCH(LARGE($C$4:$C$21,4),$C$4:$C$21,0)) -> Bookcase | C28: =INDEX($B$4:$B$21,MATCH(LARGE($C$4:$C$21,4),$C$4:$C$21,0)) -> 28429.83
A29: 5 | B29: =INDEX($A$4:$A$21,MATCH(LARGE($C$4:$C$21,5),$C$4:$C$21,0)) -> Filing Cabinet | C29: =INDEX($B$4:$B$21,MATCH(LARGE($C$4:$C$21,5),$C$4:$C$21,0)) -> 24391.89
